payra_sdk/__init__.py
payra_sdk/exceptions.py
payra_sdk/order_verification.py
payra_sdk/signature.py
payra_sdk/utils.py
payra_sdk-1.2.5.dist-info/licenses/LICENSE
payra_sdk-1.2.5.dist-info/METADATA
payra_sdk-1.2.5.dist-info/WHEEL
payra_sdk-1.2.5.dist-info/top_level.txt
payra_sdk-1.2.5.dist-info/RECORD
