Metadata-Version: 2.4
Name: payra_sdk
Version: 1.2.5
Summary: Python SDK for Payra payment signature generation (backend)
Author: Your Name
Author-email: Wraith <contact@payra.cash>
License: MIT License
Project-URL: Homepage, https://github.com/payracash
Project-URL: Source, https://github.com/payracash/payra-sdk-python
Project-URL: Issues, https://github.com/payracash/payra-sdk-python/issues
Requires-Python: >=3.8
License-File: LICENSE
Requires-Dist: web3>=6.0.0
Requires-Dist: eth-abi>=4.0.0
Requires-Dist: eth-account>=0.10.0
Requires-Dist: python-dotenv>=1.0.0
Dynamic: license-file
